[
  {
    "repo_id": "eternalmay33/08-merged_trimmed",
    "n_batches": 50,
    "batch_loss_mean": 0.05721577055752278,
    "batch_loss_std": 0.009308658570884356,
    "batch_loss_max": 0.08651533722877502,
    "sample_max_mean": 3.155601018816233,
    "sample_max_p95": 7.63315119743347,
    "sample_max_p99": 10.750096254348747,
    "sample_max_max": 15.18291187286377,
    "episode_losses": {
      "16": {
        "mean": 0.04870342214902242,
        "max_of_max": 7.838118553161621,
        "n_samples": 18
      },
      "25": {
        "mean": 0.05288094896823168,
        "max_of_max": 6.338499546051025,
        "n_samples": 15
      },
      "5": {
        "mean": 0.05898413406684995,
        "max_of_max": 5.982044219970703,
        "n_samples": 10
      },
      "13": {
        "mean": 0.06445884277277134,
        "max_of_max": 8.851207733154297,
        "n_samples": 17
      },
      "40": {
        "mean": 0.043036288374827966,
        "max_of_max": 8.21668815612793,
        "n_samples": 18
      },
      "45": {
        "mean": 0.06492542683639947,
        "max_of_max": 9.278485298156738,
        "n_samples": 17
      },
      "20": {
        "mean": 0.051400774236147605,
        "max_of_max": 7.228261470794678,
        "n_samples": 24
      },
      "44": {
        "mean": 0.042413517367094755,
        "max_of_max": 3.7775444984436035,
        "n_samples": 8
      },
      "9": {
        "mean": 0.05728386901319027,
        "max_of_max": 4.99607515335083,
        "n_samples": 7
      },
      "33": {
        "mean": 0.0689533008262515,
        "max_of_max": 7.238093852996826,
        "n_samples": 13
      },
      "3": {
        "mean": 0.0565203343414598,
        "max_of_max": 4.18790340423584,
        "n_samples": 9
      },
      "6": {
        "mean": 0.058521322990682995,
        "max_of_max": 10.345246315002441,
        "n_samples": 22
      },
      "26": {
        "mean": 0.06734987043521622,
        "max_of_max": 11.977546691894531,
        "n_samples": 11
      },
      "12": {
        "mean": 0.06350470435184737,
        "max_of_max": 12.672019004821777,
        "n_samples": 36
      },
      "8": {
        "mean": 0.04730875149834901,
        "max_of_max": 4.994144916534424,
        "n_samples": 8
      },
      "18": {
        "mean": 0.06193901744804212,
        "max_of_max": 9.328519821166992,
        "n_samples": 14
      },
      "1": {
        "mean": 0.04473698809742928,
        "max_of_max": 3.5310654640197754,
        "n_samples": 10
      },
      "48": {
        "mean": 0.05595367178320885,
        "max_of_max": 4.697562217712402,
        "n_samples": 5
      },
      "17": {
        "mean": 0.05209927490124336,
        "max_of_max": 4.248013496398926,
        "n_samples": 13
      },
      "0": {
        "mean": 0.05333533068187535,
        "max_of_max": 9.703563690185547,
        "n_samples": 24
      },
      "36": {
        "mean": 0.061601925757713616,
        "max_of_max": 13.87529182434082,
        "n_samples": 16
      },
      "14": {
        "mean": 0.06164114543103746,
        "max_of_max": 7.739656925201416,
        "n_samples": 14
      },
      "51": {
        "mean": 0.061841194302989885,
        "max_of_max": 6.490252494812012,
        "n_samples": 13
      },
      "54": {
        "mean": 0.04580788806613002,
        "max_of_max": 4.557450294494629,
        "n_samples": 14
      },
      "7": {
        "mean": 0.05863978315351738,
        "max_of_max": 12.2320556640625,
        "n_samples": 18
      },
      "28": {
        "mean": 0.08129076441613639,
        "max_of_max": 10.742430686950684,
        "n_samples": 41
      },
      "22": {
        "mean": 0.06431719604879618,
        "max_of_max": 8.48940372467041,
        "n_samples": 10
      },
      "37": {
        "mean": 0.07077254016291011,
        "max_of_max": 12.148027420043945,
        "n_samples": 11
      },
      "35": {
        "mean": 0.06598395925874893,
        "max_of_max": 8.570856094360352,
        "n_samples": 26
      },
      "38": {
        "mean": 0.056945656426250935,
        "max_of_max": 10.302472114562988,
        "n_samples": 8
      },
      "53": {
        "mean": 0.051836432169445536,
        "max_of_max": 6.659595012664795,
        "n_samples": 22
      },
      "10": {
        "mean": 0.044948249123990536,
        "max_of_max": 9.015776634216309,
        "n_samples": 20
      },
      "50": {
        "mean": 0.0783400261266665,
        "max_of_max": 9.992449760437012,
        "n_samples": 11
      },
      "52": {
        "mean": 0.05857062701963716,
        "max_of_max": 8.285557746887207,
        "n_samples": 18
      },
      "34": {
        "mean": 0.044343365017663346,
        "max_of_max": 7.736266613006592,
        "n_samples": 11
      },
      "15": {
        "mean": 0.05061488713209446,
        "max_of_max": 6.760570049285889,
        "n_samples": 26
      },
      "24": {
        "mean": 0.04376941096658508,
        "max_of_max": 5.424471855163574,
        "n_samples": 12
      },
      "41": {
        "mean": 0.06509511680765585,
        "max_of_max": 7.32961893081665,
        "n_samples": 11
      },
      "55": {
        "mean": 0.04242115332321687,
        "max_of_max": 4.96903657913208,
        "n_samples": 11
      },
      "4": {
        "mean": 0.04965534553814091,
        "max_of_max": 5.510226249694824,
        "n_samples": 19
      },
      "29": {
        "mean": 0.05314245633780956,
        "max_of_max": 7.061577796936035,
        "n_samples": 10
      },
      "39": {
        "mean": 0.07114271027967334,
        "max_of_max": 9.991039276123047,
        "n_samples": 8
      },
      "47": {
        "mean": 0.024935768141100805,
        "max_of_max": 3.810894727706909,
        "n_samples": 12
      },
      "21": {
        "mean": 0.045858109045935715,
        "max_of_max": 5.996352195739746,
        "n_samples": 23
      },
      "32": {
        "mean": 0.06057599668080608,
        "max_of_max": 13.166075706481934,
        "n_samples": 12
      },
      "11": {
        "mean": 0.08072817791253328,
        "max_of_max": 3.3074371814727783,
        "n_samples": 4
      },
      "42": {
        "mean": 0.06192816691473126,
        "max_of_max": 7.842743873596191,
        "n_samples": 10
      },
      "19": {
        "mean": 0.0668046319236358,
        "max_of_max": 4.735231876373291,
        "n_samples": 9
      },
      "23": {
        "mean": 0.06372044006219277,
        "max_of_max": 9.780045509338379,
        "n_samples": 13
      },
      "2": {
        "mean": 0.03156682522967458,
        "max_of_max": 3.2220911979675293,
        "n_samples": 8
      },
      "43": {
        "mean": 0.054130767161647476,
        "max_of_max": 15.18291187286377,
        "n_samples": 12
      },
      "31": {
        "mean": 0.05888704609658037,
        "max_of_max": 4.2880754470825195,
        "n_samples": 7
      },
      "46": {
        "mean": 0.04105871738019315,
        "max_of_max": 10.330164909362793,
        "n_samples": 11
      },
      "49": {
        "mean": 0.09859344469649452,
        "max_of_max": 10.387197494506836,
        "n_samples": 7
      },
      "30": {
        "mean": 0.04347033123485744,
        "max_of_max": 4.771140098571777,
        "n_samples": 8
      },
      "27": {
        "mean": 0.03759683051612228,
        "max_of_max": 6.808967113494873,
        "n_samples": 8
      },
      "56": {
        "mean": 0.08166194334626198,
        "max_of_max": 4.2981858253479,
        "n_samples": 7
      }
    }
  },
  {
    "repo_id": "eternalmay33/so101_real_pick_place_50eps_trimmed",
    "n_batches": 50,
    "batch_loss_mean": 0.05177677147090435,
    "batch_loss_std": 0.00908148107245966,
    "batch_loss_max": 0.0767509713768959,
    "sample_max_mean": 2.5900731990486383,
    "sample_max_p95": 6.428780627250672,
    "sample_max_p99": 10.89383489608764,
    "sample_max_max": 33.881134033203125,
    "episode_losses": {
      "34": {
        "mean": 0.045566247000048556,
        "max_of_max": 7.8895487785339355,
        "n_samples": 18
      },
      "33": {
        "mean": 0.0537371093650227,
        "max_of_max": 5.164008140563965,
        "n_samples": 23
      },
      "10": {
        "mean": 0.03774095920380205,
        "max_of_max": 6.699485778808594,
        "n_samples": 16
      },
      "4": {
        "mean": 0.09161943995526858,
        "max_of_max": 18.45082664489746,
        "n_samples": 7
      },
      "6": {
        "mean": 0.03272580658085644,
        "max_of_max": 5.285345077514648,
        "n_samples": 16
      },
      "37": {
        "mean": 0.03678762268717006,
        "max_of_max": 7.766538143157959,
        "n_samples": 59
      },
      "9": {
        "mean": 0.032119248348933,
        "max_of_max": 2.5230562686920166,
        "n_samples": 13
      },
      "49": {
        "mean": 0.04372704132563538,
        "max_of_max": 9.734482765197754,
        "n_samples": 18
      },
      "31": {
        "mean": 0.04903308982029557,
        "max_of_max": 6.429388999938965,
        "n_samples": 10
      },
      "38": {
        "mean": 0.03408051122512136,
        "max_of_max": 3.5895819664001465,
        "n_samples": 14
      },
      "8": {
        "mean": 0.052306258926788966,
        "max_of_max": 7.1879963874816895,
        "n_samples": 30
      },
      "3": {
        "mean": 0.06690999565439092,
        "max_of_max": 5.599398612976074,
        "n_samples": 18
      },
      "23": {
        "mean": 0.04113570563495159,
        "max_of_max": 5.167946815490723,
        "n_samples": 15
      },
      "39": {
        "mean": 0.052229400258511305,
        "max_of_max": 13.806225776672363,
        "n_samples": 22
      },
      "22": {
        "mean": 0.03846901965638002,
        "max_of_max": 4.077447414398193,
        "n_samples": 18
      },
      "1": {
        "mean": 0.030901964521035552,
        "max_of_max": 3.342721462249756,
        "n_samples": 22
      },
      "0": {
        "mean": 0.07343666488304734,
        "max_of_max": 33.881134033203125,
        "n_samples": 12
      },
      "7": {
        "mean": 0.05208321003352895,
        "max_of_max": 5.975693225860596,
        "n_samples": 17
      },
      "5": {
        "mean": 0.07385159780581792,
        "max_of_max": 8.15890121459961,
        "n_samples": 9
      },
      "50": {
        "mean": 0.050495539978146556,
        "max_of_max": 5.189575672149658,
        "n_samples": 25
      },
      "13": {
        "mean": 0.06910848412662744,
        "max_of_max": 6.428748607635498,
        "n_samples": 10
      },
      "11": {
        "mean": 0.03787387110402479,
        "max_of_max": 7.3719353675842285,
        "n_samples": 17
      },
      "48": {
        "mean": 0.06695686148790021,
        "max_of_max": 7.822540283203125,
        "n_samples": 24
      },
      "20": {
        "mean": 0.06683514519993748,
        "max_of_max": 11.895636558532715,
        "n_samples": 14
      },
      "36": {
        "mean": 0.06200379904891763,
        "max_of_max": 5.739725589752197,
        "n_samples": 14
      },
      "28": {
        "mean": 0.0709011158240693,
        "max_of_max": 5.4781694412231445,
        "n_samples": 7
      },
      "27": {
        "mean": 0.06117320912224906,
        "max_of_max": 9.656278610229492,
        "n_samples": 14
      },
      "47": {
        "mean": 0.043148355486874394,
        "max_of_max": 5.488827705383301,
        "n_samples": 13
      },
      "45": {
        "mean": 0.06822552531957626,
        "max_of_max": 11.713990211486816,
        "n_samples": 14
      },
      "14": {
        "mean": 0.05228894942307046,
        "max_of_max": 6.733066082000732,
        "n_samples": 14
      },
      "15": {
        "mean": 0.060691335381796725,
        "max_of_max": 6.926821231842041,
        "n_samples": 13
      },
      "19": {
        "mean": 0.04760255959505836,
        "max_of_max": 6.9398908615112305,
        "n_samples": 12
      },
      "16": {
        "mean": 0.05370641825720668,
        "max_of_max": 5.7400593757629395,
        "n_samples": 18
      },
      "25": {
        "mean": 0.06345290344740663,
        "max_of_max": 5.915651321411133,
        "n_samples": 14
      },
      "41": {
        "mean": 0.056951520343621574,
        "max_of_max": 5.304831504821777,
        "n_samples": 9
      },
      "12": {
        "mean": 0.03798822762773318,
        "max_of_max": 4.840078830718994,
        "n_samples": 17
      },
      "44": {
        "mean": 0.04039754648692906,
        "max_of_max": 2.5934295654296875,
        "n_samples": 8
      },
      "29": {
        "mean": 0.07723663076758384,
        "max_of_max": 12.099211692810059,
        "n_samples": 20
      },
      "26": {
        "mean": 0.050767779546348674,
        "max_of_max": 5.632397174835205,
        "n_samples": 19
      },
      "2": {
        "mean": 0.04687116986938885,
        "max_of_max": 4.575636863708496,
        "n_samples": 7
      },
      "32": {
        "mean": 0.04269674378964636,
        "max_of_max": 5.410678386688232,
        "n_samples": 9
      },
      "21": {
        "mean": 0.04836021875962615,
        "max_of_max": 9.172423362731934,
        "n_samples": 12
      },
      "24": {
        "mean": 0.042804390787043504,
        "max_of_max": 5.730771541595459,
        "n_samples": 18
      },
      "40": {
        "mean": 0.08032562922347676,
        "max_of_max": 6.2957072257995605,
        "n_samples": 11
      },
      "18": {
        "mean": 0.036338896568243705,
        "max_of_max": 9.13421630859375,
        "n_samples": 12
      },
      "46": {
        "mean": 0.08507803772740505,
        "max_of_max": 14.889883995056152,
        "n_samples": 17
      },
      "30": {
        "mean": 0.044425780685352426,
        "max_of_max": 6.654951572418213,
        "n_samples": 14
      },
      "17": {
        "mean": 0.05721324210365613,
        "max_of_max": 9.740503311157227,
        "n_samples": 15
      },
      "35": {
        "mean": 0.07534802389832643,
        "max_of_max": 8.14399528503418,
        "n_samples": 13
      },
      "42": {
        "mean": 0.041640763822942975,
        "max_of_max": 4.215662479400635,
        "n_samples": 10
      },
      "43": {
        "mean": 0.04337432608008385,
        "max_of_max": 4.5465779304504395,
        "n_samples": 9
      }
    }
  },
  {
    "repo_id": "eternalmay33/so101_sim_pick_place_130eps",
    "n_batches": 50,
    "batch_loss_mean": 0.09891908273100852,
    "batch_loss_std": 0.01684160790674974,
    "batch_loss_max": 0.15836173295974731,
    "sample_max_mean": 6.016310671754181,
    "sample_max_p95": 14.562563133239744,
    "sample_max_p99": 26.86725053787228,
    "sample_max_max": 43.47832489013672,
    "episode_losses": {
      "60": {
        "mean": 0.12830695807933806,
        "max_of_max": 30.614953994750977,
        "n_samples": 10
      },
      "116": {
        "mean": 0.10330720730125904,
        "max_of_max": 8.706847190856934,
        "n_samples": 10
      },
      "1": {
        "mean": 0.08708659233525395,
        "max_of_max": 11.002986907958984,
        "n_samples": 12
      },
      "113": {
        "mean": 0.08644833415746689,
        "max_of_max": 5.481926918029785,
        "n_samples": 2
      },
      "7": {
        "mean": 0.0531534303445369,
        "max_of_max": 6.651656627655029,
        "n_samples": 16
      },
      "108": {
        "mean": 0.1260949820280075,
        "max_of_max": 8.385886192321777,
        "n_samples": 3
      },
      "71": {
        "mean": 0.05832869043065743,
        "max_of_max": 6.920309543609619,
        "n_samples": 11
      },
      "25": {
        "mean": 0.07767197063991002,
        "max_of_max": 11.400794982910156,
        "n_samples": 7
      },
      "30": {
        "mean": 0.2836229205131531,
        "max_of_max": 18.26033592224121,
        "n_samples": 1
      },
      "77": {
        "mean": 0.17952155992388724,
        "max_of_max": 20.038015365600586,
        "n_samples": 10
      },
      "117": {
        "mean": 0.08697810582816601,
        "max_of_max": 6.674147605895996,
        "n_samples": 6
      },
      "67": {
        "mean": 0.08074631951749325,
        "max_of_max": 8.757818222045898,
        "n_samples": 10
      },
      "43": {
        "mean": 0.13788753747940063,
        "max_of_max": 3.9628875255584717,
        "n_samples": 1
      },
      "12": {
        "mean": 0.0772058234683105,
        "max_of_max": 20.18461036682129,
        "n_samples": 7
      },
      "15": {
        "mean": 0.09438534900546074,
        "max_of_max": 8.588383674621582,
        "n_samples": 10
      },
      "68": {
        "mean": 0.04411049522459507,
        "max_of_max": 3.5030999183654785,
        "n_samples": 5
      },
      "48": {
        "mean": 0.08470829576253891,
        "max_of_max": 8.572033882141113,
        "n_samples": 3
      },
      "97": {
        "mean": 0.08653601192470108,
        "max_of_max": 9.237741470336914,
        "n_samples": 14
      },
      "56": {
        "mean": 0.21688180090859532,
        "max_of_max": 30.462913513183594,
        "n_samples": 4
      },
      "53": {
        "mean": 0.10753326565027237,
        "max_of_max": 11.862737655639648,
        "n_samples": 5
      },
      "6": {
        "mean": 0.09363861415873874,
        "max_of_max": 8.440120697021484,
        "n_samples": 11
      },
      "126": {
        "mean": 0.06914954942961533,
        "max_of_max": 8.820869445800781,
        "n_samples": 6
      },
      "110": {
        "mean": 0.09888647283826556,
        "max_of_max": 8.47978687286377,
        "n_samples": 7
      },
      "17": {
        "mean": 0.0988672072848966,
        "max_of_max": 15.502214431762695,
        "n_samples": 31
      },
      "28": {
        "mean": 0.09862913563847542,
        "max_of_max": 10.971242904663086,
        "n_samples": 2
      },
      "3": {
        "mean": 0.04603721871972084,
        "max_of_max": 2.9407970905303955,
        "n_samples": 5
      },
      "95": {
        "mean": 0.11390184611082077,
        "max_of_max": 7.144470691680908,
        "n_samples": 3
      },
      "94": {
        "mean": 0.09159591235220432,
        "max_of_max": 5.546811103820801,
        "n_samples": 4
      },
      "85": {
        "mean": 0.07183603073159854,
        "max_of_max": 5.775973796844482,
        "n_samples": 6
      },
      "33": {
        "mean": 0.13272989727556705,
        "max_of_max": 35.83230972290039,
        "n_samples": 4
      },
      "2": {
        "mean": 0.059361883505646675,
        "max_of_max": 6.996068000793457,
        "n_samples": 14
      },
      "81": {
        "mean": 0.09426642519732316,
        "max_of_max": 8.5137300491333,
        "n_samples": 6
      },
      "27": {
        "mean": 0.08168409764766693,
        "max_of_max": 3.812652349472046,
        "n_samples": 1
      },
      "57": {
        "mean": 0.13112210761755705,
        "max_of_max": 10.963545799255371,
        "n_samples": 8
      },
      "131": {
        "mean": 0.13727225984136263,
        "max_of_max": 12.417093276977539,
        "n_samples": 6
      },
      "89": {
        "mean": 0.08443790142025266,
        "max_of_max": 9.346756935119629,
        "n_samples": 7
      },
      "87": {
        "mean": 0.07896434764067332,
        "max_of_max": 8.01383113861084,
        "n_samples": 9
      },
      "99": {
        "mean": 0.019253619015216827,
        "max_of_max": 1.2963130474090576,
        "n_samples": 2
      },
      "120": {
        "mean": 0.1122185265024503,
        "max_of_max": 17.428325653076172,
        "n_samples": 6
      },
      "82": {
        "mean": 0.1122913802973926,
        "max_of_max": 21.872385025024414,
        "n_samples": 8
      },
      "18": {
        "mean": 0.061435178853571415,
        "max_of_max": 2.8727807998657227,
        "n_samples": 4
      },
      "9": {
        "mean": 0.09283040538430214,
        "max_of_max": 7.4416961669921875,
        "n_samples": 5
      },
      "78": {
        "mean": 0.06936592608690262,
        "max_of_max": 4.825811862945557,
        "n_samples": 4
      },
      "26": {
        "mean": 0.10087997342149417,
        "max_of_max": 12.644774436950684,
        "n_samples": 15
      },
      "130": {
        "mean": 0.15616432204842567,
        "max_of_max": 16.12095069885254,
        "n_samples": 8
      },
      "8": {
        "mean": 0.0797309231840902,
        "max_of_max": 11.978386878967285,
        "n_samples": 9
      },
      "92": {
        "mean": 0.09180537536740303,
        "max_of_max": 12.979146957397461,
        "n_samples": 5
      },
      "4": {
        "mean": 0.06736610324255057,
        "max_of_max": 9.81463623046875,
        "n_samples": 7
      },
      "101": {
        "mean": 0.08555271902254649,
        "max_of_max": 5.513092041015625,
        "n_samples": 7
      },
      "124": {
        "mean": 0.10430631786584854,
        "max_of_max": 8.45773696899414,
        "n_samples": 5
      },
      "105": {
        "mean": 0.06659664213657379,
        "max_of_max": 5.8030877113342285,
        "n_samples": 1
      },
      "46": {
        "mean": 0.1485901828855276,
        "max_of_max": 15.98343276977539,
        "n_samples": 8
      },
      "75": {
        "mean": 0.1277326655884584,
        "max_of_max": 8.694640159606934,
        "n_samples": 6
      },
      "62": {
        "mean": 0.1723147208491961,
        "max_of_max": 9.935494422912598,
        "n_samples": 6
      },
      "16": {
        "mean": 0.09582414643632041,
        "max_of_max": 18.94562530517578,
        "n_samples": 9
      },
      "54": {
        "mean": 0.08103302990396817,
        "max_of_max": 12.150888442993164,
        "n_samples": 3
      },
      "14": {
        "mean": 0.09800196699798107,
        "max_of_max": 9.215572357177734,
        "n_samples": 15
      },
      "20": {
        "mean": 0.12758050007479532,
        "max_of_max": 37.491458892822266,
        "n_samples": 14
      },
      "125": {
        "mean": 0.06711401734501124,
        "max_of_max": 10.2168550491333,
        "n_samples": 10
      },
      "127": {
        "mean": 0.1570362476631999,
        "max_of_max": 14.159260749816895,
        "n_samples": 4
      },
      "114": {
        "mean": 0.15999608888075903,
        "max_of_max": 42.64281463623047,
        "n_samples": 13
      },
      "102": {
        "mean": 0.09777825623750687,
        "max_of_max": 10.16927433013916,
        "n_samples": 5
      },
      "112": {
        "mean": 0.14038662883368405,
        "max_of_max": 11.662537574768066,
        "n_samples": 11
      },
      "86": {
        "mean": 0.0694150710478425,
        "max_of_max": 22.67118263244629,
        "n_samples": 8
      },
      "52": {
        "mean": 0.12264785915613174,
        "max_of_max": 9.95677661895752,
        "n_samples": 4
      },
      "35": {
        "mean": 0.1363279327750206,
        "max_of_max": 11.023311614990234,
        "n_samples": 5
      },
      "70": {
        "mean": 0.07771682627499103,
        "max_of_max": 7.160324573516846,
        "n_samples": 5
      },
      "13": {
        "mean": 0.050968728959560394,
        "max_of_max": 4.393990516662598,
        "n_samples": 6
      },
      "129": {
        "mean": 0.08521918132901192,
        "max_of_max": 8.39406681060791,
        "n_samples": 5
      },
      "21": {
        "mean": 0.056317633328338466,
        "max_of_max": 6.243616580963135,
        "n_samples": 6
      },
      "49": {
        "mean": 0.14880595356225967,
        "max_of_max": 9.320343971252441,
        "n_samples": 4
      },
      "22": {
        "mean": 0.0970921639042596,
        "max_of_max": 37.59142303466797,
        "n_samples": 12
      },
      "5": {
        "mean": 0.05265851994045079,
        "max_of_max": 6.783779621124268,
        "n_samples": 8
      },
      "103": {
        "mean": 0.07545772262594917,
        "max_of_max": 9.396493911743164,
        "n_samples": 11
      },
      "23": {
        "mean": 0.0914330349156731,
        "max_of_max": 19.783655166625977,
        "n_samples": 19
      },
      "24": {
        "mean": 0.10324426523099343,
        "max_of_max": 17.711410522460938,
        "n_samples": 12
      },
      "93": {
        "mean": 0.08273267839103937,
        "max_of_max": 8.755255699157715,
        "n_samples": 4
      },
      "122": {
        "mean": 0.10384941659867764,
        "max_of_max": 10.025601387023926,
        "n_samples": 4
      },
      "107": {
        "mean": 0.0742250345647335,
        "max_of_max": 6.867225646972656,
        "n_samples": 4
      },
      "64": {
        "mean": 0.06263135299086571,
        "max_of_max": 12.974355697631836,
        "n_samples": 5
      },
      "111": {
        "mean": 0.08330380637198687,
        "max_of_max": 10.68154239654541,
        "n_samples": 4
      },
      "115": {
        "mean": 0.24832109361886978,
        "max_of_max": 9.528115272521973,
        "n_samples": 2
      },
      "10": {
        "mean": 0.05919343554838137,
        "max_of_max": 7.253365516662598,
        "n_samples": 11
      },
      "40": {
        "mean": 0.144028190523386,
        "max_of_max": 11.986050605773926,
        "n_samples": 4
      },
      "41": {
        "mean": 0.11865995327631633,
        "max_of_max": 12.295010566711426,
        "n_samples": 6
      },
      "128": {
        "mean": 0.1521910180648168,
        "max_of_max": 10.883283615112305,
        "n_samples": 3
      },
      "98": {
        "mean": 0.06322979535907507,
        "max_of_max": 15.04465389251709,
        "n_samples": 10
      },
      "36": {
        "mean": 0.15140082873404026,
        "max_of_max": 15.801609992980957,
        "n_samples": 4
      },
      "84": {
        "mean": 0.08674955864747365,
        "max_of_max": 7.878923416137695,
        "n_samples": 6
      },
      "61": {
        "mean": 0.09016962349414825,
        "max_of_max": 14.169851303100586,
        "n_samples": 7
      },
      "50": {
        "mean": 0.07176372669637203,
        "max_of_max": 10.616710662841797,
        "n_samples": 5
      },
      "0": {
        "mean": 0.05534786805510521,
        "max_of_max": 4.105729103088379,
        "n_samples": 5
      },
      "74": {
        "mean": 0.09228119738399983,
        "max_of_max": 13.408279418945312,
        "n_samples": 10
      },
      "83": {
        "mean": 0.061911992728710175,
        "max_of_max": 8.211579322814941,
        "n_samples": 2
      },
      "47": {
        "mean": 0.2699225055319922,
        "max_of_max": 43.47832489013672,
        "n_samples": 7
      },
      "65": {
        "mean": 0.09507835780580838,
        "max_of_max": 22.60422706604004,
        "n_samples": 9
      },
      "32": {
        "mean": 0.043869748711586,
        "max_of_max": 1.5386672019958496,
        "n_samples": 1
      },
      "59": {
        "mean": 0.07791768440178462,
        "max_of_max": 6.6470947265625,
        "n_samples": 7
      },
      "79": {
        "mean": 0.047828908730298283,
        "max_of_max": 5.85883092880249,
        "n_samples": 10
      },
      "90": {
        "mean": 0.17124400412042937,
        "max_of_max": 12.775379180908203,
        "n_samples": 6
      },
      "80": {
        "mean": 0.03740319050848484,
        "max_of_max": 2.1189661026000977,
        "n_samples": 2
      },
      "73": {
        "mean": 0.09991640597581863,
        "max_of_max": 6.241687774658203,
        "n_samples": 4
      },
      "44": {
        "mean": 0.13989592716097832,
        "max_of_max": 17.4754638671875,
        "n_samples": 2
      },
      "58": {
        "mean": 0.10946059475342433,
        "max_of_max": 20.342472076416016,
        "n_samples": 6
      },
      "55": {
        "mean": 0.13910306245088577,
        "max_of_max": 14.245333671569824,
        "n_samples": 3
      },
      "11": {
        "mean": 0.09406351558864116,
        "max_of_max": 10.17823314666748,
        "n_samples": 10
      },
      "96": {
        "mean": 0.12369807437062263,
        "max_of_max": 17.735572814941406,
        "n_samples": 2
      },
      "69": {
        "mean": 0.061290815472602844,
        "max_of_max": 13.26956558227539,
        "n_samples": 2
      },
      "88": {
        "mean": 0.09705460288872321,
        "max_of_max": 10.84099006652832,
        "n_samples": 12
      },
      "39": {
        "mean": 0.09785264357924461,
        "max_of_max": 10.717033386230469,
        "n_samples": 4
      },
      "76": {
        "mean": 0.11708390216032664,
        "max_of_max": 9.376123428344727,
        "n_samples": 3
      },
      "121": {
        "mean": 0.13027885369956493,
        "max_of_max": 18.994182586669922,
        "n_samples": 4
      },
      "123": {
        "mean": 0.042634304612874985,
        "max_of_max": 4.602882385253906,
        "n_samples": 2
      },
      "63": {
        "mean": 0.08802195706150749,
        "max_of_max": 16.451053619384766,
        "n_samples": 11
      },
      "104": {
        "mean": 0.10738533238569896,
        "max_of_max": 9.017861366271973,
        "n_samples": 3
      },
      "109": {
        "mean": 0.08140621334314346,
        "max_of_max": 3.9782910346984863,
        "n_samples": 2
      },
      "29": {
        "mean": 0.18259118497371674,
        "max_of_max": 20.626907348632812,
        "n_samples": 1
      },
      "19": {
        "mean": 0.08773871857140746,
        "max_of_max": 8.954684257507324,
        "n_samples": 7
      },
      "38": {
        "mean": 0.31820584274828434,
        "max_of_max": 21.379255294799805,
        "n_samples": 2
      },
      "100": {
        "mean": 0.15347588062286377,
        "max_of_max": 5.559274673461914,
        "n_samples": 1
      },
      "106": {
        "mean": 0.03791626915335655,
        "max_of_max": 3.1342318058013916,
        "n_samples": 1
      },
      "119": {
        "mean": 0.06719915568828583,
        "max_of_max": 3.5243172645568848,
        "n_samples": 1
      },
      "66": {
        "mean": 0.13767153024673462,
        "max_of_max": 5.254322052001953,
        "n_samples": 1
      },
      "37": {
        "mean": 0.12058396823704243,
        "max_of_max": 19.568031311035156,
        "n_samples": 4
      },
      "72": {
        "mean": 0.03479732200503349,
        "max_of_max": 2.5652315616607666,
        "n_samples": 2
      }
    }
  }
]